librmm/GIT_COMMIT
librmm/VERSION
librmm/__init__.py
librmm/_version.py
librmm/include/nvtx3/nvToolsExt.h
librmm/include/nvtx3/nvToolsExtCuda.h
librmm/include/nvtx3/nvToolsExtCudaRt.h
librmm/include/nvtx3/nvToolsExtOpenCL.h
librmm/include/nvtx3/nvToolsExtSync.h
librmm/include/nvtx3/nvtx3.hpp
librmm/include/nvtx3/nvtxDetail/nvtxImpl.h
librmm/include/nvtx3/nvtxDetail/nvtxImplCore.h
librmm/include/nvtx3/nvtxDetail/nvtxImplCudaRt_v3.h
librmm/include/nvtx3/nvtxDetail/nvtxImplCuda_v3.h
librmm/include/nvtx3/nvtxDetail/nvtxImplOpenCL_v3.h
librmm/include/nvtx3/nvtxDetail/nvtxImplSync_v3.h
librmm/include/nvtx3/nvtxDetail/nvtxInit.h
librmm/include/nvtx3/nvtxDetail/nvtxInitDecls.h
librmm/include/nvtx3/nvtxDetail/nvtxInitDefs.h
librmm/include/nvtx3/nvtxDetail/nvtxLinkOnce.h
librmm/include/nvtx3/nvtxDetail/nvtxTypes.h
librmm/include/rapids/cub/agent/agent_adjacent_difference.cuh
librmm/include/rapids/cub/agent/agent_batch_memcpy.cuh
librmm/include/rapids/cub/agent/agent_for.cuh
librmm/include/rapids/cub/agent/agent_histogram.cuh
librmm/include/rapids/cub/agent/agent_merge.cuh
librmm/include/rapids/cub/agent/agent_merge_sort.cuh
librmm/include/rapids/cub/agent/agent_radix_sort_downsweep.cuh
librmm/include/rapids/cub/agent/agent_radix_sort_histogram.cuh
librmm/include/rapids/cub/agent/agent_radix_sort_onesweep.cuh
librmm/include/rapids/cub/agent/agent_radix_sort_upsweep.cuh
librmm/include/rapids/cub/agent/agent_reduce.cuh
librmm/include/rapids/cub/agent/agent_reduce_by_key.cuh
librmm/include/rapids/cub/agent/agent_rle.cuh
librmm/include/rapids/cub/agent/agent_scan.cuh
librmm/include/rapids/cub/agent/agent_scan_by_key.cuh
librmm/include/rapids/cub/agent/agent_segment_fixup.cuh
librmm/include/rapids/cub/agent/agent_segmented_radix_sort.cuh
librmm/include/rapids/cub/agent/agent_select_if.cuh
librmm/include/rapids/cub/agent/agent_spmv_orig.cuh
librmm/include/rapids/cub/agent/agent_sub_warp_merge_sort.cuh
librmm/include/rapids/cub/agent/agent_three_way_partition.cuh
librmm_cu12-25.4.0.dist-info/METADATA
librmm_cu12-25.4.0.dist-info/WHEEL
librmm_cu12-25.4.0.dist-info/entry_points.txt
librmm_cu12-25.4.0.dist-info/licenses/LICENSE
librmm_cu12-25.4.0.dist-info/RECORD
