Metadata-Version: 2.1
Name: librmm-cu12
Version: 25.4.0
Summary: rmm - RAPIDS Memory Manager
Author: NVIDIA Corporation
License: Apache-2.0
Classifier: Intended Audience :: Developers
Classifier: Topic :: Database
Classifier: Topic :: Scientific/Engineering
Classifier: License :: OSI Approved :: Apache Software License
Classifier: Programming Language :: C++
Classifier: Environment :: GPU :: NVIDIA CUDA
Project-URL: Homepage, https://github.com/rapidsai/rmm
Requires-Dist: rapids-logger==0.1.*
